furax/__init__.py
furax/_config.py
furax/exceptions.py
furax/tree.py
furax/_instruments/__init__.py
furax/_instruments/sat.py
furax/_instruments/sky.py
furax/core/__init__.py
furax/core/_axes.py
furax/core/_base.py
furax/core/_blocks.py
furax/core/_dense.py
furax/core/_diagonal.py
furax/core/_indices.py
furax/core/_linear.py
furax/core/_sum.py
furax/core/_toeplitz.py
furax/core/_trees.py
furax/core/rules.py
furax/core/utils.py
furax/interfaces/__init__.py
furax/interfaces/toast/__init__.py
furax/interfaces/toast/obs_matrix.py
furax/obs/__init__.py
furax/obs/_detectors.py
furax/obs/_likelihoods.py
furax/obs/_projections.py
furax/obs/_samplings.py
furax/obs/landscapes.py
furax/obs/stokes.py
furax/obs/operators/__init__.py
furax/obs/operators/_hwp.py
furax/obs/operators/_polarizers.py
furax/obs/operators/_qu_rotations.py
furax/obs/operators/_seds.py
furax/preprocessing/__init__.py
furax/preprocessing/gap_filling.py
furax-0.9.dist-info/METADATA
furax-0.9.dist-info/WHEEL
furax-0.9.dist-info/top_level.txt
furax-0.9.dist-info/RECORD
