Metadata-Version: 2.1
Name: furax
Version: 0.9
Summary: Operators and solvers for high-performance computing.
Author: Wassim Kabalan
Author-email: Pierre Chanial <chanial@apc.in2p3.fr>, Simon Biquard <biquard@apc.in2p3.fr>
Maintainer-email: Pierre Chanial <chanial@apc.in2p3.fr>
Project-URL: homepage, https://scipol.in2p3.fr
Project-URL: repository, https://github.com/CMBSciPol/furax
Keywords: scientific computing
Classifier: Programming Language :: Python
Classifier: Programming Language :: Python :: 3
Classifier: Intended Audience :: Science/Research
Classifier: Operating System :: OS Independent
Classifier: Topic :: Scientific/Engineering
Requires-Python: >=3.10
Requires-Dist: jaxtyping
Requires-Dist: healpy>=0.16.6
Requires-Dist: jax-healpy
Requires-Dist: jax-dataclasses
Requires-Dist: lineax
Requires-Dist: numpy
Requires-Dist: scipy
Requires-Dist: matplotlib
Requires-Dist: astropy
Requires-Dist: typing-extensions; python_version < "3.11"
Provides-Extra: comp_sep
Requires-Dist: pysm3; extra == "comp-sep"
Provides-Extra: dev
Requires-Dist: pytest; extra == "dev"
Requires-Dist: pytest-cov; extra == "dev"
Requires-Dist: pytest-mock; extra == "dev"
Requires-Dist: pytest-insubprocess>=1.1; extra == "dev"
Requires-Dist: setuptools-scm; extra == "dev"
Requires-Dist: beartype; extra == "dev"
Provides-Extra: docs
Requires-Dist: sphinx>=5.0; extra == "docs"
Requires-Dist: sphinx-book-theme>=1.0; extra == "docs"
Requires-Dist: sphinx-copybutton>=0.5; extra == "docs"
Requires-Dist: myst-parser>=1.0; extra == "docs"
Requires-Dist: nbsphinx>=0.8; extra == "docs"
Requires-Dist: ipykernel>=6.0; extra == "docs"
